{"@context":"http://iiif.io/api/presentation/2/context.json","@id":"https://detektiiif.manducus.net/invalide","@type":"sc:Collection","label":"detektIIIF2 Collection","manifests":[{"@id":"https://api.digitale-sammlungen.de/iiif/presentation/v2/bsb00071690/manifest","@type":"sc:Manifest","label":"Wolfram, von Eschenbach: Parzifal, Titurel und Tagelieder - BSB Cgm 19","thumbnail":"https://api.digitale-sammlungen.de/iiif/image/v2/bsb00071690_00003/full/280,/0/default.jpg"},{"@id":"https://www.e-manuscripta.ch/i3f/v20/1537172/manifest","@type":"sc:Manifest","label":"[Schweizerchronik bis zum Jahre 1534]","thumbnail":"https://www.e-manuscripta.ch/i3f/v21/1539366/full/304/0/default.jpg"},{"@id":"https://www.e-manuscripta.ch/i3f/v20/819732/manifest","@type":"sc:Manifest","label":"[Weltbild der Dayak]","thumbnail":"https://www.e-manuscripta.ch/i3f/v21/819734/full/304/0/default.jpg"}]}
